dist_util/__init__.py
dist_util/context.py
dist_util/core.py
dist_util/decorators.py
dist_util/ops.py
dist_util/py.typed
dist_util/utils.py
dist_util-0.1.0.dist-info/METADATA
dist_util-0.1.0.dist-info/WHEEL
dist_util-0.1.0.dist-info/RECORD
