Metadata-Version: 2.4
Name: dist-util
Version: 0.1.0
Summary: Pytorch Distributed Utilities
Author-email: Tony Francis <tony@dream3d.com>, Vikaas Varma <vik@dream3d.com>
Requires-Python: >=3.10
Requires-Dist: torch>=2.7.0
